Workbook

Sheet Summary
A1: Axis Bank — Key Customer Profitability Ratios, Q1FY27 (Standalone)
A2: Each value links to the sheet where it is calculated.
A4: Ratio | B4: Segment | C4: Value | D4: Formula | E4: Sheet
A5: 1. Segment PBT Margin | B5: Corporate / Wholesale | C5: ='1_PBT_Margin'!D6 | D5: PBT ÷ gross revenue | E5: 1_PBT_Margin
A6: 1. Segment PBT Margin | B6: Retail (total) | C6: ='1_PBT_Margin'!D7 | D6: PBT ÷ gross revenue | E6: 1_PBT_Margin
A7: 2. Credit Mix Share | B7: Retail | C7: ='2_Credit_Mix'!F6 | D7: Segment advances ÷ net advances | E7: 2_Credit_Mix
A8: 2. Credit Mix Share | B8: Corporate | C8: ='2_Credit_Mix'!F7 | D8: Segment advances ÷ net advances | E8: 2_Credit_Mix
A9: 2. Credit Mix Share | B9: SME | C9: ='2_Credit_Mix'!F8 | D9: Segment advances ÷ net advances | E9: 2_Credit_Mix
A10: 3. CASA Ratio (MEB) | B10: Bank | C10: ='3_CASA'!C15 | D10: (SA + CA) ÷ total deposits | E10: 3_CASA
A11: 4. Liabilities-to-Assets | B11: Retail (total) | C11: ='4_Liab_to_Assets'!D6 | D11: Liabilities ÷ assets | E11: 4_Liab_to_Assets
A12: 4. Liabilities-to-Assets | B12: Corporate / Wholesale | C12: ='4_Liab_to_Assets'!D9 | D12: Liabilities ÷ assets | E12: 4_Liab_to_Assets
A13: 5. Share of Gross Slippages | B13: Retail | C13: ='5_Asset_Stress'!F6 | D13: Segment ÷ bank gross slippages | E13: 5_Asset_Stress
A15: Segment comparison matrix → | E15: 6_Segment_Matrix
A17: Colour key: blue = hard-coded input from source files · black = formula · green = link to another sheet · yellow fill = headline ratio. All amounts in ₹ crore.

Sheet 1_PBT_Margin
A1: Ratio 1 · Segment PBT Margin — Q1FY27 (Standalone)
A2: Formula: Segment Profit Before Tax ÷ Gross Segment Revenue × 100
A3: Rupees of profit kept from every ₹100 of segment revenue (revenue includes internal FTP adjustments).
A5: Segment | B5: Gross segment revenue (₹ cr) | C5: Segment PBT (₹ cr) | D5: PBT margin | E5: Source
A6: Corporate / Wholesale | B6: 14167.5 | C6: 3358.26 | D6: =IF(B6=0,"",C6/B6) | E6: Axis Bank Data file 1.pdf, p.5
A7: Retail (total) | B7: 38269.3 | C7: 3565.52 | D7: =IF(B7=0,"",C7/B7) | E7: Axis Bank Data file 1.pdf, p.5
A8: ↳ Digital Banking | B8: 10627.32 | C8: 1531.43 | D8: =IF(B8=0,"",C8/B8) | E8: Axis Bank Data file 1.pdf, p.5
A9: ↳ Other Retail | B9: 27641.98 | C9: 2034.09 | D9: =IF(B9=0,"",C9/B9) | E9: Axis Bank Data file 1.pdf, p.5
A10: Treasury | B10: 8487.17 | C10: 1663.85 | D10: =IF(B10=0,"",C10/B10) | E10: Axis Bank Data file 1.pdf, p.5
A11: Other Banking Business | B11: 915.57 | C11: 848.93 | D11: =IF(B11=0,"",C11/B11) | E11: Axis Bank Data file 1.pdf, p.5
A14: Trend — PBT margin by quarter
A15: Segment | B15: Revenue Q1FY26 (₹ cr) | C15: PBT Q1FY26 (₹ cr) | D15: Revenue Q4FY26 (₹ cr) | E15: PBT Q4FY26 (₹ cr) | F15: Revenue Q1FY27 (₹ cr) | G15: PBT Q1FY27 (₹ cr) | H15: Margin Q1FY26 | I15: Margin Q4FY26 | J15: Margin Q1FY27 | K15: Δ Q1FY26→Q1FY27
A16: Corporate / Wholesale | B16: 11806.71 | C16: 2737.21 | D16: 12913.54 | E16: 2139.85 | F16: 14167.5 | G16: 3358.26 | H16: =C16/B16 | I16: =E16/D16 | J16: =G16/F16 | K16: =(J16-H16)*100
A17: Retail (total) | B17: 35631.6 | C17: 1435.87 | D17: 36865.29 | E17: 2473.14 | F17: 38269.3 | G17: 3565.52 | H17: =C17/B17 | I17: =E17/D17 | J17: =G17/F17 | K17: =(J17-H17)*100
A18: Digital Banking | B18: 9405.36 | C18: 576.45 | D18: 10302.66 | E18: 1340.41 | F18: 10627.32 | G18: 1531.43 | H18: =C18/B18 | I18: =E18/D18 | J18: =G18/F18 | K18: =(J18-H18)*100
A19: Other Retail | B19: 26226.24 | C19: 859.42 | D19: 26562.63 | E19: 1132.73 | F19: 27641.98 | G19: 2034.09 | H19: =C19/B19 | I19: =E19/D19 | J19: =G19/F19 | K19: =(J19-H19)*100
A20: Treasury | B20: 8419.72 | C20: 2423.32 | D20: 7015.71 | E20: 303.32 | F20: 8487.17 | G20: 1663.85 | H20: =C20/B20 | I20: =E20/D20 | J20: =G20/F20 | K20: =(J20-H20)*100
A22: Margins use gross segment revenue (before inter-segment elimination), so they are not comparable with the bank's reported margins.
A23: Colour key: blue = hard-coded input from source files · black = formula · green = link to another sheet · yellow fill = headline ratio. All amounts in ₹ crore.

Sheet 2_Credit_Mix
A1: Ratio 2 · Credit Mix Share — Jun-2026 vs Jun-2025
A2: Formula: Segment Advances ÷ Total Bank Net Advances × 100
A3: How much of the bank's total loan book (credit risk) is allocated to each customer profile.
A5: Loan segment | B5: Advances Jun-2025 (₹ cr) | C5: Advances Jun-2026 (₹ cr) | D5: YoY growth | E5: Share Jun-2025 | F5: Share Jun-2026 | G5: Mix shift | H5: Source
A6: Retail | B6: 622960 | C6: 675546 | D6: =C6/B6-1 | E6: =B6/B$9 | F6: =C6/C$9 | G6: =(F6-E6)*100 | H6: Axis Bank press release (additional metrics), p.8
A7: Corporate | B7: 315892 | C7: 434392 | D7: =C7/B7-1 | E7: =B7/B$9 | F7: =C7/C$9 | G7: =(F7-E7)*100 | H7: Axis Bank press release (additional metrics), p.8
A8: SME | B8: 120872 | C8: 151619 | D8: =C8/B8-1 | E8: =B8/B$9 | F8: =C8/C$9 | G8: =(F8-E8)*100 | H8: Axis Bank press release (additional metrics), p.8
A9: Total net advances | B9: =SUM(B6:B8) | C9: =SUM(C6:C8) | D9: =C9/B9-1 | E9: =SUM(E6:E8) | F9: =SUM(F6:F8)
A10: Reported net advances (check) | B10: 1059724 | C10: 1261557
A11: Difference (should be 0) | B11: =B9-B10 | C11: =C9-C10
A13: Colour key: blue = hard-coded input from source files · black = formula · green = link to another sheet · yellow fill = headline ratio. All amounts in ₹ crore.

Sheet 3_CASA
A1: Ratio 3 · CASA Ratio (month-end balance basis)
A2: Formula: CASA Deposits (Savings + Current Accounts) ÷ Total Deposits × 100
A3: Funding quality — share of low-cost, sticky relationship deposits vs expensive term deposits.
A5: Deposit line (month-end, ₹ cr) | B5: Jun-2025 | C5: Jun-2026 | D5: YoY growth | E5: Source
A6: Savings Bank deposits (SA) | B6: 305133 | C6: 348312 | D6: =C6/B6-1 | E6: Axis Bank press release (additional metrics), p.8
A7: Current Account deposits (CA) | B7: 163033 | C7: 173386 | D7: =C7/B7-1 | E7: Axis Bank press release (additional metrics), p.8
A8: CASA deposits | B8: =B6+B7 | C8: =C6+C7 | D8: =C8/B8-1
A9: Term deposits | B9: 693449 | C9: 851238 | D9: =C9/B9-1 | E9: Axis Bank press release (additional metrics), p.8
A10: Total deposits | B10: =B8+B9 | C10: =C8+C9 | D10: =C10/B10-1
A11: Reported total deposits (check) | B11: 1161615 | C11: 1372936
A12: Difference (should be 0) | B12: =B10-B11 | C12: =C10-C11
A14: Ratio | B14: Jun-2025 | C14: Jun-2026 | D14: Change
A15: CASA ratio | B15: =B8/B$10 | C15: =C8/C$10 | D15: =(C15-B15)*100
A16: Savings share of deposits | B16: =B6/B$10 | C16: =C6/C$10 | D16: =(C16-B16)*100
A17: Current account share of deposits | B17: =B7/B$10 | C17: =C7/C$10 | D17: =(C17-B17)*100
A18: Term deposit share | B18: =B9/B$10 | C18: =C9/C$10 | D18: =(C18-B18)*100
A20: Month-end balance (MEB) basis. The bank also reports CASA on a quarterly-average (QAB) basis (~37% for Q1FY27); do not mix the two.
A21: Colour key: blue = hard-coded input from source files · black = formula · green = link to another sheet · yellow fill = headline ratio. All amounts in ₹ crore.

Sheet 4_Liab_to_Assets
A1: Ratio 4 · Liabilities-to-Assets — Q1FY27 (Standalone)
A2: Formula: Segment Liabilities ÷ Segment Assets
A3: Funding dependency: >1.0x = segment raises more deposits than it lends (provider); <1.0x = uses the bank's liquidity (user).
A5: Segment | B5: Segment assets (₹ cr) | C5: Segment liabilities (₹ cr) | D5: Liabilities ÷ assets | E5: Net funding position (₹ cr) | F5: Funding role | G5: Source
A6: Retail (total) | B6: 686713.79 | C6: 1131328.3 | D6: =C6/B6 | E6: =C6-B6 | F6: =IF(D6>1,"Net liquidity provider","Net liquidity user") | G6: Axis Bank Data file 1.pdf, p.5
A7: ↳ Digital Banking | B7: 153578.3 | C7: 230504.61 | D7: =C7/B7 | E7: =C7-B7 | F7: =IF(D7>1,"Net liquidity provider","Net liquidity user") | G7: Axis Bank Data file 1.pdf, p.5
A8: ↳ Other Retail | B8: 533135.49 | C8: 900823.72 | D8: =C8/B8 | E8: =C8-B8 | F8: =IF(D8>1,"Net liquidity provider","Net liquidity user") | G8: Axis Bank Data file 1.pdf, p.5
A9: Corporate / Wholesale | B9: 598488.96 | C9: 237696.61 | D9: =C9/B9 | E9: =C9-B9 | F9: =IF(D9>1,"Net liquidity provider","Net liquidity user") | G9: Axis Bank Data file 1.pdf, p.5
A10: Treasury | B10: 626906.76 | C10: 332810.15 | D10: =C10/B10 | E10: =C10-B10 | F10: =IF(D10>1,"Net liquidity provider","Net liquidity user") | G10: Axis Bank Data file 1.pdf, p.5
A11: Other Banking Business | B11: 1064.84 | C11: 37.07 | D11: =C11/B11 | E11: =C11-B11 | F11: =IF(D11>1,"Net liquidity provider","Net liquidity user") | G11: Axis Bank Data file 1.pdf, p.5
A13: Retail surplus ÷ Corporate funding gap | D13: =E6/-E9
A15: Trend — liabilities-to-assets by quarter
A16: Segment | B16: Assets Q1FY26 (₹ cr) | C16: Liabilities Q1FY26 (₹ cr) | D16: Assets Q4FY26 (₹ cr) | E16: Liabilities Q4FY26 (₹ cr) | F16: Assets Q1FY27 (₹ cr) | G16: Liabilities Q1FY27 (₹ cr) | H16: L/A Q1FY26 | I16: L/A Q4FY26 | J16: L/A Q1FY27
A17: Retail (total) | B17: 637810.14 | C17: 925882.23 | D17: 686599.21 | E17: 1077946.8 | F17: 686713.79 | G17: 1131328.3 | H17: =C17/B17 | I17: =E17/D17 | J17: =G17/F17
A18: Corporate / Wholesale | B18: 447232.12 | C18: 219843.64 | D18: 571029.14 | E18: 254472.26 | F18: 598488.96 | G18: 237696.61 | H18: =C18/B18 | I18: =E18/D18 | J18: =G18/F18
A19: Treasury | B19: 510734.13 | C19: 264326.67 | D19: 619567.76 | E19: 342691.86 | F19: 626906.76 | G19: 332810.15 | H19: =C19/B19 | I19: =E19/D19 | J19: =G19/F19
A21: Colour key: blue = hard-coded input from source files · black = formula · green = link to another sheet · yellow fill = headline ratio. All amounts in ₹ crore.

Sheet 5_Asset_Stress
A1: Ratio 5 · Segment Contribution to Total Asset Stress — Q1FY27
A2: Formula: Segment Gross Slippages ÷ Total Bank Gross Slippages × 100
A3: Which customer segment generated the fresh loan defaults (slippages) during the quarter.
A5: Slippage segment (earnings call) | B5: Mapped loan bucket | C5: Gross slippages (₹ cr) | D5: Net slippages (₹ cr) | E5: Advances Jun-2026 (₹ cr) | F5: Share of gross slippages | G5: Share of net slippages | H5: Share of loans | I5: Gross slippage rate (annualised) | J5: Source
A6: Retail | B6: Retail | C6: 5176 | D6: 3204 | E6: ='2_Credit_Mix'!C6 | F6: =C6/C$9 | G6: =D6/D$9 | H6: =E6/E$9 | I6: =C6*4/E6 | J6: Axis Bank earnings call data, p.7
A7: CBG | B7: SME | C7: 266 | D7: 210 | E7: ='2_Credit_Mix'!C8 | F7: =C7/C$9 | G7: =D7/D$9 | H7: =E7/E$9 | I7: =C7*4/E7 | J7: Axis Bank earnings call data, p.7
A8: Wholesale (WBCG) | B8: Corporate | C8: 124 | D8: 26 | E8: ='2_Credit_Mix'!C7 | F8: =C8/C$9 | G8: =D8/D$9 | H8: =E8/E$9 | I8: =C8*4/E8 | J8: Axis Bank earnings call data, p.7
A9: Total | C9: =SUM(C6:C8) | D9: =SUM(D6:D8) | E9: =SUM(E6:E8) | F9: =SUM(F6:F8) | G9: =SUM(G6:G8) | H9: =SUM(H6:H8) | I9: =C9*4/E9
A10: Reported bank slippages (check) | C10: 5566 | D10: 3440
A11: Difference (should be 0) | C11: =C9-C10 | D11: =D9-D10
A13: Mapping CBG→SME and WBCG→Corporate is approximate; treat slippage rates as indicative. Rate = quarterly slippages × 4 ÷ period-end advances.
A14: Colour key: blue = hard-coded input from source files · black = formula · green = link to another sheet · yellow fill = headline ratio. All amounts in ₹ crore.

Sheet 6_Segment_Matrix
A1: Segment Comparison Matrix — Q1FY27 (Standalone)
A2: Formula: Inputs (blue) feed every metric below; each metric row is colour-scaled across segments
A3: Green = best and red = worst on that metric, using the 'Better if' direction. Uncoloured rows are descriptive.
A5: Inputs (₹ cr) | B5: Corporate / Wholesale | C5: Retail (total) | D5: Digital Banking | E5: Other Retail | F5: Treasury | G5: Bank total | H5: Source
A6: Gross segment revenue | B6: 14167.5 | C6: 38269.3 | D6: 10627.32 | E6: 27641.98 | F6: 8487.17 | G6: 61839.54 | H6: Data file 1, p.5
A7: Segment PBT | B7: 3358.26 | C7: 3565.52 | D7: 1531.43 | E7: 2034.09 | F7: 1663.85 | G7: 9436.56 | H7: Data file 1, p.5
A8: Segment assets | B8: 598488.96 | C8: 686713.79 | D8: 153578.3 | E8: 533135.49 | F8: 626906.76 | G8: 1921966.2 | H8: Data file 1, p.5
A9: Segment liabilities | B9: 237696.61 | C9: 1131328.3 | D9: 230504.61 | E9: 900823.72 | F9: 332810.15 | G9: 1710272.8 | H9: Data file 1, p.5
A10: Gross segment revenue Q1FY26 | B10: 11806.71 | C10: 35631.6 | D10: 9405.36 | E10: 26226.24 | F10: 8419.72 | G10: 56915.5 | H10: Data file 1, p.5
A11: Segment PBT Q1FY26 | B11: 2737.21 | C11: 1435.87 | D11: 576.45 | E11: 859.42 | F11: 2423.32 | G11: 7567.5 | H11: Data file 1, p.5
A12: Customer advances (Jun-26) | B12: 586011 | C12: 675546 | G12: 1261557 | H12: Press release, p.8
A13: Gross slippages | B13: 390 | C13: 5176 | G13: 5566 | H13: Earnings call, p.7
A15: Metric | B15: Corporate / Wholesale | C15: Retail (total) | D15: Digital Banking | E15: Other Retail | F15: Treasury | G15: Better if
A16: Profitability
A17: PBT margin | B17: =IF(B$6=0,"n/a",B$7/B$6) | C17: =IF(C$6=0,"n/a",C$7/C$6) | D17: =IF(D$6=0,"n/a",D$7/D$6) | E17: =IF(E$6=0,"n/a",E$7/E$6) | F17: =IF(F$6=0,"n/a",F$7/F$6) | G17: higher
A18: Return on segment assets (annualised) | B18: =B$7*4/B$8 | C18: =C$7*4/C$8 | D18: =D$7*4/D$8 | E18: =E$7*4/E$8 | F18: =F$7*4/F$8 | G18: higher
A19: Growth
A20: Revenue growth YoY (vs Q1FY26) | B20: =B$6/B$10-1 | C20: =C$6/C$10-1 | D20: =D$6/D$10-1 | E20: =E$6/E$10-1 | F20: =F$6/F$10-1 | G20: higher
A21: PBT growth YoY (vs Q1FY26) | B21: =B$7/B$11-1 | C21: =C$7/C$11-1 | D21: =D$7/D$11-1 | E21: =E$7/E$11-1 | F21: =F$7/F$11-1 | G21: higher
A22: Contribution
A23: Share of bank revenue (gross) | B23: =B$6/$G$6 | C23: =C$6/$G$6 | D23: =D$6/$G$6 | E23: =E$6/$G$6 | F23: =F$6/$G$6 | G23: –
A24: Share of bank PBT | B24: =B$7/$G$7 | C24: =C$7/$G$7 | D24: =D$7/$G$7 | E24: =E$7/$G$7 | F24: =F$7/$G$7 | G24: –
A25: Share of bank assets | B25: =B$8/$G$8 | C25: =C$8/$G$8 | D25: =D$8/$G$8 | E25: =E$8/$G$8 | F25: =F$8/$G$8 | G25: –
A26: Share of bank liabilities | B26: =B$9/$G$9 | C26: =C$9/$G$9 | D26: =D$9/$G$9 | E26: =E$9/$G$9 | F26: =F$9/$G$9 | G26: –
A27: Funding
A28: Liabilities-to-assets | B28: =B$9/B$8 | C28: =C$9/C$8 | D28: =D$9/D$8 | E28: =E$9/E$8 | F28: =F$9/F$8 | G28: higher
A29: Net funding position (₹ cr) | B29: =B$9-B$8 | C29: =C$9-C$8 | D29: =D$9-D$8 | E29: =E$9-E$8 | F29: =F$9-F$8 | G29: –
A30: Credit risk
A31: Credit mix share | B31: =IF(B$12="","n/a",B$12/$G$12) | C31: =IF(C$12="","n/a",C$12/$G$12) | D31: =IF(D$12="","n/a",D$12/$G$12) | E31: =IF(E$12="","n/a",E$12/$G$12) | F31: =IF(F$12="","n/a",F$12/$G$12) | G31: –
A32: Share of gross slippages | B32: =IF(B$13="","n/a",B$13/$G$13) | C32: =IF(C$13="","n/a",C$13/$G$13) | D32: =IF(D$13="","n/a",D$13/$G$13) | E32: =IF(E$13="","n/a",E$13/$G$13) | F32: =IF(F$13="","n/a",F$13/$G$13) | G32: lower
A33: Gross slippage rate (annualised) | B33: =IF(OR(B$13="",B$12=""),"n/a",B$13*4/B$12) | C33: =IF(OR(C$13="",C$12=""),"n/a",C$13*4/C$12) | D33: =IF(OR(D$13="",D$12=""),"n/a",D$13*4/D$12) | E33: =IF(OR(E$13="",E$12=""),"n/a",E$13*4/E$12) | F33: =IF(OR(F$13="",F$12=""),"n/a",F$13*4/F$12) | G33: lower
A35: Corporate/Wholesale advances and slippages = Corporate + SME (WBCG + CBG). Loan and slippage data are not split for Digital, Other Retail or Treasury (n/a).
A36: Annualised figures = quarterly value × 4 ÷ period-end balance. Revenue shares use gross revenue before inter-segment elimination.
A37: Colour key: blue = hard-coded input from source files · black = formula · green = link to another sheet · yellow fill = headline ratio. All amounts in ₹ crore.

Sheet Integrity_Checks
A1: Integrity checks — components reconcile to reported totals
A3: Check | B3: Computed | C3: Reported | D3: Difference | E3: Pass
A4: Σ segment revenue = total segment revenue | B4: 61839.54 | C4: 61839.54 | D4: =B4-C4 | E4: =IF(ABS(D4)<=1,"PASS","CHECK")
A5: Σ revenue − inter-segment = income from operations | B5: 40721.05 | C5: 40721.05 | D5: =B5-C5 | E5: =IF(ABS(D5)<=1,"PASS","CHECK")
A6: Σ segment PBT = bank PBT | B6: 9436.56 | C6: 9436.56 | D6: =B6-C6 | E6: =IF(ABS(D6)<=1,"PASS","CHECK")
A7: Σ segment assets = total assets | B7: 1921966.2 | C7: 1921966.2 | D7: =B7-C7 | E7: =IF(ABS(D7)<=1,"PASS","CHECK")
A8: Σ segment liabilities = total segment liabilities | B8: 1710272.8 | C8: 1710272.8 | D8: =B8-C8 | E8: =IF(ABS(D8)<=1,"PASS","CHECK")
A9: Retail revenue = Digital + Other Retail | B9: 38269.3 | C9: 38269.3 | D9: =B9-C9 | E9: =IF(ABS(D9)<=1,"PASS","CHECK")
A10: Retail PBT = Digital + Other Retail | B10: 3565.52 | C10: 3565.52 | D10: =B10-C10 | E10: =IF(ABS(D10)<=1,"PASS","CHECK")
A11: Σ segment PBT = P&L profit before tax | B11: 9436.56 | C11: 9436.56 | D11: =B11-C11 | E11: =IF(ABS(D11)<=1,"PASS","CHECK")
A12: Corporate + SME + Retail advances = net advances | B12: 1261557 | C12: 1261557 | D12: =B12-C12 | E12: =IF(ABS(D12)<=1,"PASS","CHECK")
A13: SA + CA = CASA (MEB) | B13: 521698 | C13: 521698 | D13: =B13-C13 | E13: =IF(ABS(D13)<=1,"PASS","CHECK")
A14: CASA + Term = total deposits (MEB) | B14: 1372936 | C14: 1372936 | D14: =B14-C14 | E14: =IF(ABS(D14)<=1,"PASS","CHECK")
A15: Press-release deposits = balance-sheet deposits | B15: 1372936 | C15: 1372935.7 | D15: =B15-C15 | E15: =IF(ABS(D15)<=1,"PASS","CHECK")
A16: Retail + CBG + Wholesale slippages = bank slippages | B16: 5566 | C16: 5566 | D16: =B16-C16 | E16: =IF(ABS(D16)<=1,"PASS","CHECK")
A18: Tolerance ±₹1 cr (press-release figures are rounded to whole crore).
